lenspack/__init__.py
lenspack/info.py
lenspack/peaks.py
lenspack/shear.py
lenspack/stats.py
lenspack/utils.py
lenspack/geometry/__init__.py
lenspack/geometry/measures.py
lenspack/geometry/projections/__init__.py
lenspack/geometry/projections/gnom.py
lenspack/halo/__init__.py
lenspack/halo/fitting.py
lenspack/halo/profiles.py
lenspack/image/__init__.py
lenspack/image/filters.py
lenspack/image/inpainting.py
lenspack/image/inversion.py
lenspack/image/transforms.py
lenspack/tests/__init__.py
lenspack/tests/test_geometry.py
lenspack/theory/__init__.py
lenspack/theory/cosmology.py
lenspack/theory/distributions.py
lenspack-1.0.0.dist-info/METADATA
lenspack-1.0.0.dist-info/RECORD
lenspack-1.0.0.dist-info/WHEEL
lenspack-1.0.0.dist-info/top_level.txt
