Metadata-Version: 2.1
Name: lenspack
Version: 1.0.0
Summary: builtins Author: Austin Peel, Email: austin.peel@cea.fr, Year: 2019, A collection of weak lensing tools in Python
Home-page: https://github.com/austinpeel/lenspack
Author: Austin Peel
Author-email: austin.peel@cea.fr
License: MIT
Platform: UNKNOWN
Requires-Dist: numpy
Requires-Dist: scipy
Requires-Dist: astropy
